identiconify/__init__.py
identiconify/base.py
identiconify/pil_identicon.py
identiconify-0.1.0.dist-info/METADATA
identiconify-0.1.0.dist-info/WHEEL
identiconify-0.1.0.dist-info/licenses/LICENSE
identiconify-0.1.0.dist-info/RECORD
