Metadata-Version: 2.4
Name: identiconify
Version: 0.1.0
Summary: Python identicon generator
Project-URL: Repository, https://github.com/M4hbod/Identiconify
Author-email: M4hbod <me@mahbod.dev>
License: MIT
License-File: LICENSE
Requires-Python: >=3.9
Requires-Dist: pillow>=11.2.1
